[
  {
    "md5": "336b0353e904ce21d9b52b4a474a82ad",
    "url": "https://raw.github.com/cfHxqA/InnoGames.FoE.Bot/master/Bot.exe"
  },
  {
    "md5": "40b04411da4932376ae11f3c59b7c54f",
    "url": "https://raw.github.com/cfHxqA/InnoGames.FoE.Bot/master/Bot.exe.config"
  },
  {
    "md5": "99676fd59a3f9441168cb6e4b3ddffd0",
    "url": "https://raw.github.com/cfHxqA/InnoGames.FoE.Bot/master/config.json"
  },
  {
    "md5": "a9db97665b4c89ad8c3e46c0e3c0bb11",
    "url": "https://raw.github.com/cfHxqA/InnoGames.FoE.Bot/master/Core/BotNix.InnoGames.FoE.dll"
  },
  {
    "md5": "0fff8c8d28594f8eca61bd66dc73f423",
    "url": "https://raw.github.com/cfHxqA/InnoGames.FoE.Bot/master/Core/BotNix.InnoGames.FoE.Plugin.dll"
  }
]